{
  "tz": "Europe/Paris",
  "avg_utc_iso": "2026-01-17T17:45:42.250Z",
  "now_iso": "2026-01-17T18:45:42+01:00",
  "now_unix_ms": 1768671942250,
  "sources": [
    {
      "name": "quelle-heure-est-il.com",
      "url": "https://quelle-heure-est-il.com/fr/heure/paris",
      "date": null,
      "unix_ms": null
    },
    {
      "name": "time.is",
      "url": "https://time.is/Paris",
      "date": "Sat, 17 Jan 2026 17:45:42 GMT",
      "unix_ms": 1768671942000
    },
    {
      "name": "timeanddate.com",
      "url": "https://www.timeanddate.com/worldclock/france/paris",
      "date": "Sat, 17 Jan 2026 17:45:42 GMT",
      "unix_ms": 1768671942000
    },
    {
      "name": "google.fr",
      "url": "https://www.google.fr",
      "date": "Sat, 17 Jan 2026 17:45:42 GMT",
      "unix_ms": 1768671942000
    },
    {
      "name": "cloudflare.com",
      "url": "https://www.cloudflare.com",
      "date": "Sat, 17 Jan 2026 17:45:43 GMT",
      "unix_ms": 1768671943000
    }
  ],
  "delta_between_sources_ms": 750,
  "status": "ok"
}