{
  "tz": "Europe/Paris",
  "avg_utc_iso": "2026-02-07T15:54:30.750Z",
  "now_iso": "2026-02-07T16:54:30+01:00",
  "now_unix_ms": 1770479670750,
  "sources": [
    {
      "name": "quelle-heure-est-il.com",
      "url": "https://quelle-heure-est-il.com/fr/heure/paris",
      "date": null,
      "unix_ms": null
    },
    {
      "name": "time.is",
      "url": "https://time.is/Paris",
      "date": "Sat, 07 Feb 2026 15:54:30 GMT",
      "unix_ms": 1770479670000
    },
    {
      "name": "timeanddate.com",
      "url": "https://www.timeanddate.com/worldclock/france/paris",
      "date": "Sat, 07 Feb 2026 15:54:31 GMT",
      "unix_ms": 1770479671000
    },
    {
      "name": "google.fr",
      "url": "https://www.google.fr",
      "date": "Sat, 07 Feb 2026 15:54:31 GMT",
      "unix_ms": 1770479671000
    },
    {
      "name": "cloudflare.com",
      "url": "https://www.cloudflare.com",
      "date": "Sat, 07 Feb 2026 15:54:31 GMT",
      "unix_ms": 1770479671000
    }
  ],
  "delta_between_sources_ms": 750,
  "status": "ok"
}