{
  "tz": "Europe/Paris",
  "avg_utc_iso": "2025-11-26T21:20:27.000Z",
  "now_iso": "2025-11-26T22:20:27+01:00",
  "now_unix_ms": 1764192027000,
  "sources": [
    {
      "name": "quelle-heure-est-il.com",
      "url": "https://quelle-heure-est-il.com/fr/heure/paris",
      "date": null,
      "unix_ms": null
    },
    {
      "name": "time.is",
      "url": "https://time.is/Paris",
      "date": "Wed, 26 Nov 2025 21:20:25 GMT",
      "unix_ms": 1764192025000
    },
    {
      "name": "timeanddate.com",
      "url": "https://www.timeanddate.com/worldclock/france/paris",
      "date": "Wed, 26 Nov 2025 21:20:25 GMT",
      "unix_ms": 1764192025000
    },
    {
      "name": "google.fr",
      "url": "https://www.google.fr",
      "date": null,
      "unix_ms": null
    },
    {
      "name": "cloudflare.com",
      "url": "https://www.cloudflare.com",
      "date": "Wed, 26 Nov 2025 21:20:31 GMT",
      "unix_ms": 1764192031000
    }
  ],
  "delta_between_sources_ms": 4000,
  "status": "ok"
}