{
  "tz": "Europe/Paris",
  "avg_utc_iso": "2025-12-04T19:45:25.500Z",
  "now_iso": "2025-12-04T20:45:25+01:00",
  "now_unix_ms": 1764877525500,
  "sources": [
    {
      "name": "quelle-heure-est-il.com",
      "url": "https://quelle-heure-est-il.com/fr/heure/paris",
      "date": null,
      "unix_ms": null
    },
    {
      "name": "time.is",
      "url": "https://time.is/Paris",
      "date": "Thu, 04 Dec 2025 19:45:25 GMT",
      "unix_ms": 1764877525000
    },
    {
      "name": "timeanddate.com",
      "url": "https://www.timeanddate.com/worldclock/france/paris",
      "date": "Thu, 04 Dec 2025 19:45:25 GMT",
      "unix_ms": 1764877525000
    },
    {
      "name": "google.fr",
      "url": "https://www.google.fr",
      "date": "Thu, 04 Dec 2025 19:45:26 GMT",
      "unix_ms": 1764877526000
    },
    {
      "name": "cloudflare.com",
      "url": "https://www.cloudflare.com",
      "date": "Thu, 04 Dec 2025 19:45:26 GMT",
      "unix_ms": 1764877526000
    }
  ],
  "delta_between_sources_ms": 500,
  "status": "ok"
}