{
  "tz": "Europe/Paris",
  "avg_utc_iso": "2025-11-06T14:53:39.000Z",
  "now_iso": "2025-11-06T15:53:39+01:00",
  "now_unix_ms": 1762440819000,
  "sources": [
    {
      "name": "quelle-heure-est-il.com",
      "url": "https://quelle-heure-est-il.com/fr/heure/paris",
      "date": null,
      "unix_ms": null
    },
    {
      "name": "time.is",
      "url": "https://time.is/Paris",
      "date": "Thu, 06 Nov 2025 14:53:38 GMT",
      "unix_ms": 1762440818000
    },
    {
      "name": "timeanddate.com",
      "url": "https://www.timeanddate.com/worldclock/france/paris",
      "date": "Thu, 06 Nov 2025 14:53:39 GMT",
      "unix_ms": 1762440819000
    },
    {
      "name": "google.fr",
      "url": "https://www.google.fr",
      "date": "Thu, 06 Nov 2025 14:53:39 GMT",
      "unix_ms": 1762440819000
    },
    {
      "name": "cloudflare.com",
      "url": "https://www.cloudflare.com",
      "date": "Thu, 06 Nov 2025 14:53:40 GMT",
      "unix_ms": 1762440820000
    }
  ],
  "delta_between_sources_ms": 1000,
  "status": "ok"
}